[
  {
    "year": "2024",
    "events": [
      " 1er Lugar Campeonato Nacional Ica U13 Damas",
      " 2do Lugar Campeonato Nacional Ica U12 Damas",
      " 1er Lugar Campeonato Internacional Encesta Copa Spalding U17 Varones",
      " 2do Lugar Campeonato Internacional Encesta Copa Spalding U13 Varones",
      " 2do Lugar Liga de Lima U15 Varones",
      " 2do Lugar Liga de Lima U17 Varones",
      " 1er Lugar Campeonato Nacional Liga de San Borja U15 Damas",
      " Aportamos 8 jugadores a la selecci贸n de Lima",
      " Aportamos 1 entrenador a la selecci贸n de Lima",
      " 4 categor铆as llegaron a semifinales de la Liga de Lima"
    ]
  },
  {
    "year": "2023",
    "events": [
      " Campeones Liga de Lima U19 Varones",
      " Subcampeones Liga de Lima U13 Damas",
      " Tercer Lugar Liga de Lima U17 Varones",
      " Aportamos 5 jugadores a la selecci贸n de Lima",
      " Aportamos 1 entrenador y 1 asistente a la selecci贸n de Lima"
    ]
  },
  {
    "year": "2022",
    "events": [
      " Finalistas Liga de Lima U15 Damas",
      " Creaci贸n de la rama masculina",
      "5to lugar U19 Varones Liga de Lima"
    ]
  },
  {
    "year": "2021",
    "events": [" Virtualidad Zoomamericano"]
  },
  {
    "year": "2020",
    "events": [
      " Campeones Copa Azurmendy Chile",
      " Campeones Copa Los Lagos Chile"
    ]
  },
  {
    "year": "2019",
    "events": [
      "06 Enero - Nace Basketcenter",
      " Campeones Liga de Lima U12 Damas",
      "4to lugar Liga de Lima U13 Damas"
    ]
  }
]
